README.md
setup.py
ldmnqSDK/__init__.py
ldmnqSDK/ldmnqSDK.py
ldmnqSDK.egg-info/PKG-INFO
ldmnqSDK.egg-info/SOURCES.txt
ldmnqSDK.egg-info/dependency_links.txt
ldmnqSDK.egg-info/top_level.txt